brainet/__init__.py
brainet/cli.py
brainet/ai/__init__.py
brainet/ai/groq_client.py
brainet/ai/session_summarizer.py
brainet/core/__init__.py
brainet/core/config.py
brainet/core/context_capture.py
brainet/core/analysis/__init__.py
brainet/core/analysis/ast_parser.py
brainet/core/analysis/context_analyzer.py
brainet/core/analysis/file_scanner.py
brainet/core/analysis/project_context.py
brainet/core/analysis/semantic_searcher.py
brainet/core/extractors/__init__.py
brainet/core/extractors/command_extractor.py
brainet/core/extractors/file_extractor.py
brainet/core/extractors/git_extractor.py
brainet/core/extractors/todo_extractor.py
brainet/storage/__init__.py
brainet/storage/capsule_manager.py
brainet/storage/models/__init__.py
brainet/storage/models/capsule.py
brainet/utils/errors.py
brainet/utils/patterns.py
brainet-0.2.3.dist-info/LICENSE
brainet-0.2.3.dist-info/METADATA
brainet-0.2.3.dist-info/WHEEL
brainet-0.2.3.dist-info/entry_points.txt
brainet-0.2.3.dist-info/top_level.txt
brainet-0.2.3.dist-info/RECORD
