Metadata-Version: 2.1
Name: brainet
Version: 0.2.3
Summary: AI-powered development context tracker - never lose your train of thought
Home-page: https://github.com/meetxiv/brainet
Author: Meet Joshi
Author-email: meetxiv@gmail.com
License: MIT
Project-URL: Bug Reports, https://github.com/meetxiv/brainet/issues
Project-URL: Source, https://github.com/meetxiv/brainet
Project-URL: Documentation, https://github.com/meetxiv/brainet#readme
Keywords: ai development context git productivity claude groq llm developer-tools cli
Platform: UNKNOWN
Classifier: Development Status :: 4 - Beta
Classifier: Intended Audience :: Developers
Classifier: Topic :: Software Development :: Version Control :: Git
Classifier: Topic :: Software Development :: Libraries :: Python Modules
Classifier: Topic :: Utilities
Classifier: License :: OSI Approved :: MIT License
Classifier: Programming Language :: Python :: 3
Classifier: Programming Language :: Python :: 3.8
Classifier: Programming Language :: Python :: 3.9
Classifier: Programming Language :: Python :: 3.10
Classifier: Programming Language :: Python :: 3.11
Classifier: Programming Language :: Python :: 3.12
Classifier: Operating System :: OS Independent
Classifier: Environment :: Console
Requires-Python: >=3.8
License-File: LICENSE
Requires-Dist: click (==8.1.7)
Requires-Dist: rich (==13.9.0)
Requires-Dist: gitpython (==3.1.43)
Requires-Dist: openai (==1.46.0)
Requires-Dist: watchdog (==3.0.0)
Requires-Dist: anthropic (>=0.3.0)
Requires-Dist: groq (>=0.4.0)
Requires-Dist: aiohttp (==3.13.1)
Requires-Dist: fastapi (==0.120.0)
Requires-Dist: uvicorn (==0.38.0)
Requires-Dist: pydantic (==2.12.3)
Requires-Dist: starlette (==0.48.0)
Requires-Dist: pytest (==8.0.0)
Requires-Dist: pytest-asyncio (==0.23.5)
Requires-Dist: tqdm (==4.66.1)
Requires-Dist: python-dotenv (==1.0.0)
Requires-Dist: sqlalchemy (==2.0.25)
Requires-Dist: numpy (==1.26.3)
Requires-Dist: pyyaml (==6.0.1)
